{
"type": "FeatureCollection",
"crs": { "type": "name", "properties": { "name": "urn:ogc:def:crs:OGC:1.3:CRS84" } },
                                                                                
"features": [
{ "type": "Feature", "properties": { "NAME": "Fort Salisbury", "ARRIVAL": "12 September 1890", "NOTES": "Laager and Camp built here", "type": "fort" }, "geometry": { "type": "Point", "coordinates": [ 31.051413600932481, -17.829351616745196 ] } },
{ "type": "Feature", "properties": { "NAME": "Fort Tuli", "ARRIVAL": "3 July 1890", "NOTES": "Fort building progresses as drift was being built.", "type": "fort" }, "geometry": { "type": "Point", "coordinates": [ 29.180981667804375, -21.91038331050385 ] } },
{ "type": "Feature", "properties": { "NAME": "Fort Victoria", "ARRIVAL": "Undated", "NOTES": "Place where Fort Victoria 2 was finally built", "type": "fort" }, "geometry": { "type": "Point", "coordinates": [ 30.831548078674036, -20.072824556528566 ] } },
{ "type": "Feature", "properties": { "NAME": "Fort Charter", "ARRIVAL": "4 September 1890", "NOTES": "Built and garrisoned by 'A' Troop (Police).", "type": "fort" }, "geometry": { "type": "Point", "coordinates": [ 31.062305071897661, -18.594934659136289 ] } }
]
}
